{
  "articles": [
    {
      "id": 435,
      "link_url": "https://bingo.boohee.com/api/v1/knowledges/1517825989.html?share=true",
      "pic_url": "http://one.boohee.cn/bingo/image/knowledge/2018/2/5/062014ec7162b87f296fa4918ada709d?imageView2/1/w/240/h/180",
      "title": "注意！这些行为都会导致姨妈出走！",
      "first_category": null,
      "click_count": 8348,
      "knowledge_type": "normal"
    },
    {
      "id": 434,
      "link_url": "https://bingo.boohee.com/api/v1/knowledges/1517564752.html?share=true",
      "pic_url": "http://one.boohee.cn/bingo/image/knowledge/2018/2/2/e3d087115a8a56bce597b33fde96c138?imageView2/1/w/240/h/180",
      "title": "体重增加了先别哭，这个点才更重要",
      "first_category": null,
      "click_count": 9061,
      "knowledge_type": "normal"
    },
    {
      "id": 432,
      "link_url": "https://bingo.boohee.com/api/v1/knowledges/1517389548.html?share=true",
      "pic_url": "http://one.boohee.cn/bingo/image/knowledge/2018/1/31/c3961157a50385c155dcad3c1aeb3098?imageView2/1/w/240/h/180",
      "title": "别急着嫌自己胖，先搞懂这个再说",
      "first_category": null,
      "click_count": 74730,
      "knowledge_type": "normal"
    },
    {
      "id": 430,
      "link_url": "https://bingo.boohee.com/api/v1/knowledges/1517219383.html?share=true",
      "pic_url": "http://one.boohee.cn/bingo/image/knowledge/2018/1/29/9476aaafefa9223cc75080d8ade46654?imageView2/1/w/240/h/180",
      "title": "过年怕胖？这两个小操作能让你开心很多",
      "first_category": null,
      "click_count": 11854,
      "knowledge_type": "normal"
    },
    {
      "id": 427,
      "link_url": "https://bingo.boohee.com/api/v1/knowledges/1516934464.html?share=true",
      "pic_url": "http://one.boohee.cn/bingo/image/knowledge/2018/1/26/2e209cdfb9d2261cb920df67f8be7e8a?imageView2/1/w/240/h/180",
      "title": "想要一双好看的腿？这些方法千万别试",
      "first_category": null,
      "click_count": 9147,
      "knowledge_type": "normal"
    },
    {
      "id": 425,
      "link_url": "https://bingo.boohee.com/api/v1/knowledges/1516785155.html?share=true",
      "pic_url": "http://one.boohee.cn/bingo/image/knowledge/2018/1/24/724e5c61fdf5c427aec90e63b23a9196?imageView2/1/w/240/h/180",
      "title": "不想过年体重疯长，今天一定要做这件事",
      "first_category": null,
      "click_count": 12613,
      "knowledge_type": "normal"
    },
    {
      "id": 421,
      "link_url": "https://bingo.boohee.com/api/v1/knowledges/1516355624.html?share=true",
      "pic_url": "http://one.boohee.cn/bingo/image/knowledge/2018/1/19/c27f0aa4651f7d670fe8d6b298802f95?imageView2/1/w/240/h/180",
      "title": "90%的女生都有的痛，简单一步搞定",
      "first_category": null,
      "click_count": 5407,
      "knowledge_type": "normal"
    },
    {
      "id": 412,
      "link_url": "https://bingo.boohee.com/api/v1/knowledges/1515582466.html?share=true",
      "pic_url": "http://one.boohee.cn/bingo/image/knowledge/2018/1/10/0ec6fbee3f503432fccb54a0ef341875?imageView2/1/w/240/h/180",
      "title": "你为什么胖？因为营养不良！",
      "first_category": null,
      "click_count": 38774,
      "knowledge_type": "normal"
    },
    {
      "id": 373,
      "link_url": "https://bingo.boohee.com/api/v1/knowledges/1512035772.html?share=true",
      "pic_url": "http://one.boohee.cn/bingo/image/knowledge/2017/11/30/77323f06289a80852ed0a12c266a3269?imageView2/1/w/240/h/180",
      "title": "你不在意的那些坏习惯，都会让你脱发！",
      "first_category": null,
      "click_count": 35198,
      "knowledge_type": "normal"
    },
    {
      "id": 356,
      "link_url": "https://bingo.boohee.com/api/v1/knowledges/1510047569.html?share=true",
      "pic_url": "http://one.boohee.cn/bingo/image/knowledge/2017/11/7/f5a2320e9d487f1f480928e5f224d6b3?imageView2/1/w/240/h/180",
      "title": "据说不跳这个坑都不算减过肥，你中过招吗？",
      "first_category": null,
      "click_count": 43776,
      "knowledge_type": "normal"
    },
    {
      "id": 352,
      "link_url": "https://bingo.boohee.com/api/v1/knowledges/1509528662.html?share=true",
      "pic_url": "http://one.boohee.cn/bingo/image/knowledge/2017/11/1/63eb02e670e045dd3846a17b219f5ab6?imageView2/1/w/240/h/180",
      "title": "99%的人都会遇到的减肥难题，4个字就能解决",
      "first_category": null,
      "click_count": 43936,
      "knowledge_type": "normal"
    },
    {
      "id": 348,
      "link_url": "https://bingo.boohee.com/api/v1/knowledges/1509006291.html?share=true",
      "pic_url": "http://one.boohee.cn/bingo/image/knowledge/2017/10/26/e79076d88e73d63d8377e2558aae302e?imageView2/1/w/240/h/180",
      "title": "减肥最易犯的3个常识性错误，你可别再中招了",
      "first_category": null,
      "click_count": 48132,
      "knowledge_type": "normal"
    },
    {
      "id": 346,
      "link_url": "https://bingo.boohee.com/api/v1/knowledges/1508836312.html?share=true",
      "pic_url": "http://one.boohee.cn/bingo/image/knowledge/2017/10/24/ad8882ae32f87665f197e4cf522feed5?imageView2/1/w/240/h/180",
      "title": "每天最易发胖的4个时间点，控制住你就瘦了！",
      "first_category": null,
      "click_count": 114784,
      "knowledge_type": "normal"
    },
    {
      "id": 342,
      "link_url": "https://bingo.boohee.com/api/v1/knowledges/1508238134.html?share=true",
      "pic_url": "http://one.boohee.cn/bingo/image/knowledge/2017/10/17/a5481a0dffdae3241f94545040a27ed7?imageView2/1/w/240/h/180",
      "title": "天冷瘦得慢？你需要一份秋冬减肥攻略",
      "first_category": null,
      "click_count": 67989,
      "knowledge_type": "normal"
    }
  ],
  "page": 0,
  "total_pages": 1
}